LICENSE.txt
README.md
setup.py
.idea/misc.xml
.idea/modules.xml
.idea/orange3-example-addon-master.iml
.idea/vcs.xml
.idea/workspace.xml
.idea/inspectionProfiles/Project_Default.xml
.idea/inspectionProfiles/profiles_settings.xml
Orange3_Audio_IJS.egg-info/PKG-INFO
Orange3_Audio_IJS.egg-info/SOURCES.txt
Orange3_Audio_IJS.egg-info/dependency_links.txt
Orange3_Audio_IJS.egg-info/entry_points.txt
Orange3_Audio_IJS.egg-info/namespace_packages.txt
Orange3_Audio_IJS.egg-info/requires.txt
Orange3_Audio_IJS.egg-info/top_level.txt
orangecontrib/__init__.py
orangecontrib/audio/audio_filter.py
orangecontrib/audio/feature_extraction.py
orangecontrib/audio/segmentation.py
orangecontrib/audio/feature_extraction/Linux/SMILExtract
orangecontrib/audio/feature_extraction/Win32/SMILExtract_Release.exe
orangecontrib/audio/feature_extraction/Win32/SMILExtract_ReleasePortaudio.exe
orangecontrib/audio/feature_extraction/Win32/chroma.csv
orangecontrib/audio/feature_extraction/Win32/desktop.ini
orangecontrib/audio/feature_extraction/Win32/openSMILEbatchGUI.exe
orangecontrib/audio/feature_extraction/Win32/openSmileLib_Release.dll
orangecontrib/audio/feature_extraction/Win32/openSmileLib_ReleasePortaudio.dll
orangecontrib/audio/feature_extraction/Win32/portaudio_x86.dll
orangecontrib/audio/feature_extraction/Win32/wrapper.exe
orangecontrib/audio/feature_extraction/config/IS09_emotion.conf
orangecontrib/audio/feature_extraction/config/IS10_paraling.conf
orangecontrib/audio/feature_extraction/config/IS10_paraling_compat.conf
orangecontrib/audio/feature_extraction/config/IS11_speaker_state.conf
orangecontrib/audio/feature_extraction/config/IS12_speaker_trait.conf
orangecontrib/audio/feature_extraction/config/IS12_speaker_trait_compat.conf
orangecontrib/audio/feature_extraction/config/IS13_ComParE.conf
orangecontrib/audio/feature_extraction/config/IS13_ComParE_Voc.conf
orangecontrib/audio/feature_extraction/config/MFCC12_0_D_A.conf
orangecontrib/audio/feature_extraction/config/MFCC12_0_D_A_Z.conf
orangecontrib/audio/feature_extraction/config/MFCC12_E_D_A.conf
orangecontrib/audio/feature_extraction/config/MFCC12_E_D_A_Z.conf
orangecontrib/audio/feature_extraction/config/PLP_0_D_A.conf
orangecontrib/audio/feature_extraction/config/PLP_0_D_A_Z.conf
