Metadata-Version: 1.1
Name: Orange3-Audio-IJS
Version: 0.1
Summary: Add-on for audio preprocessing and classification.
Home-page: https://github.com/BuDnA/Audio-IJS
Author: Department of Intelligent Systems | Jožef Stefan Institute - IJS
Author-email: info@ijs.si
License: GSL3+
Keywords: orange3 add-on,orange3-audio-ijs
Platform: UNKNOWN
Classifier: Development Status :: 1 - Planning
Classifier: Intended Audience :: Education
Classifier: Intended Audience :: Science/Research
Classifier: License :: OSI Approved :: GNU General Public License v3 or later (GPLv3+)
Classifier: Programming Language :: Python :: 3 :: Only
